h_pyramid_sentry/__init__.py
h_pyramid_sentry/event.py
h_pyramid_sentry/event_filter.py
h_pyramid_sentry/exceptions.py
h_pyramid_sentry/subscribers.py
h_pyramid_sentry/filters/__init__.py
h_pyramid_sentry/filters/pyramid.py
h_pyramid_sentry-1.2.4.dist-info/LICENSE
h_pyramid_sentry-1.2.4.dist-info/METADATA
h_pyramid_sentry-1.2.4.dist-info/WHEEL
h_pyramid_sentry-1.2.4.dist-info/top_level.txt
h_pyramid_sentry-1.2.4.dist-info/RECORD
