Metadata-Version: 2.1
Name: h-pyramid-sentry
Version: 1.2.4
Summary: A library which integrates Sentry logging into Pyramid with the ability to filter out unwanted messages.
Home-page: https://github.com/hypothesis/h-pyramid-sentry
Project-URL: Bug Tracker, https://github.com/hypothesis/h-pyramid-sentry/issues
Project-URL: Changelog, https://github.com/hypothesis/h-pyramid-sentry/releases
Classifier: Programming Language :: Python :: 3
Classifier: License :: OSI Approved :: BSD License
Classifier: Intended Audience :: Developers
Requires-Python: >=3.8
License-File: LICENSE
Requires-Dist: sentry-sdk
Requires-Dist: pyramid
